is_number/__init__.py
is_number/_version.py
is_number/is_number.py
is_number_test-0.0.2.dist-info/LICENSE
is_number_test-0.0.2.dist-info/METADATA
is_number_test-0.0.2.dist-info/WHEEL
is_number_test-0.0.2.dist-info/top_level.txt
is_number_test-0.0.2.dist-info/RECORD
